[
  {"bagic_key":"1231", "transaction_id":"123123123", "merchant_id":"nbsbasd", "csc_transaction_no":"12312312"},
  {"bagic_key":"1232", "transaction_id":"123123123", "merchant_id":"nbsbasd", "csc_transaction_no":"12312312"},
  {"bagic_key":"1233", "transaction_id":"123123123", "merchant_id":"nbsbasd", "csc_transaction_no":"12312312"},
  {"bagic_key":"1234", "transaction_id":"123123123", "merchant_id":"nbsbasd", "csc_transaction_no":"12312312"},
  {"bagic_key":"1235", "transaction_id":"123123123", "merchant_id":"nbsbasd", "csc_transaction_no":"12312312"},
  {"bagic_key":"1236", "transaction_id":"123123123", "merchant_id":"nbsbasd", "csc_transaction_no":"12312312"},
  {"bagic_key":"1237", "transaction_id":"123123123", "merchant_id":"nbsbasd", "csc_transaction_no":"12312312"}
]
